ehtim/__init__.py
ehtim/array.py
ehtim/caltable.py
ehtim/const_def.py
ehtim/diagnostics.py
ehtim/image.py
ehtim/imager.py
ehtim/model.py
ehtim/movie.py
ehtim/obsdata.py
ehtim/parloop.py
ehtim/survey.py
ehtim/vex.py
ehtim/calibrating/__init__.py
ehtim/calibrating/cal_helpers.py
ehtim/calibrating/network_cal.py
ehtim/calibrating/pol_cal.py
ehtim/calibrating/pol_cal_new.py
ehtim/calibrating/polgains_cal.py
ehtim/calibrating/self_cal.py
ehtim/features/__init__.py
ehtim/features/rex.py
ehtim/imaging/__init__.py
ehtim/imaging/clean.py
ehtim/imaging/dynamical_imaging.py
ehtim/imaging/imager_utils.py
ehtim/imaging/linearize_energy.py
ehtim/imaging/multifreq_imager_utils.py
ehtim/imaging/patch_prior.py
ehtim/imaging/pol_imager_utils.py
ehtim/imaging/starwarps.py
ehtim/io/__init__.py
ehtim/io/load.py
ehtim/io/oifits.py
ehtim/io/save.py
ehtim/io/writeoifits.py
ehtim/modeling/__init__.py
ehtim/modeling/modeling_utils.py
ehtim/observing/__init__.py
ehtim/observing/obs_helpers.py
ehtim/observing/obs_simulate.py
ehtim/observing/pulses.py
ehtim/plotting/__init__.py
ehtim/plotting/comp_plots.py
ehtim/plotting/comparisons.py
ehtim/plotting/summary_plots.py
ehtim/scattering/__init__.py
ehtim/scattering/stochastic_optics.py
ehtim/statistics/__init__.py
ehtim/statistics/dataframes.py
ehtim/statistics/stats.py
ehtim-1.2.10.data/scripts/calibrate.py
ehtim-1.2.10.data/scripts/cleanup.py
ehtim-1.2.10.data/scripts/cli_blur_comp.py
ehtim-1.2.10.data/scripts/gendata.py
ehtim-1.2.10.data/scripts/imaging.py
ehtim-1.2.10.data/scripts/imgsum.py
ehtim-1.2.10.data/scripts/verify_gradients.py
scripts/calibrate.py
scripts/cleanup.py
scripts/cli_blur_comp.py
scripts/gendata.py
scripts/imaging.py
scripts/imgsum.py
scripts/pipeline.py
scripts/verify_gradients.py
ehtim-1.2.10.dist-info/LICENSE.txt
ehtim-1.2.10.dist-info/METADATA
ehtim-1.2.10.dist-info/WHEEL
ehtim-1.2.10.dist-info/top_level.txt
ehtim-1.2.10.dist-info/RECORD
