Metadata-Version: 2.1
Name: ehtim
Version: 1.2.10
Summary: Imaging, analysis, and simulation software for radio interferometry
Home-page: https://github.com/achael/eht-imaging
Download-URL: https://github.com/achael/eht-imaging/archive/v1.2.9.tar.gz
Author: Andrew Chael
Author-email: achael@princeton.edu
License: GPLv3
Keywords: imaging astronomy EHT polarimetry
Classifier: Development Status :: 3 - Alpha
Classifier: Intended Audience :: Developers
Classifier: Topic :: Software Development :: Build Tools
Classifier: License :: OSI Approved :: GNU General Public License v3 (GPLv3)
Classifier: Programming Language :: Python :: 3.8
License-File: LICENSE.txt
Requires-Dist: numpy>=1.24
Requires-Dist: scipy>=1.9.3
Requires-Dist: astropy>=5.0.4
Requires-Dist: matplotlib>=3.7.3
Requires-Dist: skyfield
Requires-Dist: h5py
Requires-Dist: pandas
Requires-Dist: requests
Requires-Dist: future
Requires-Dist: networkx
Requires-Dist: paramsurvey
